{"name":"Operational Services (SV)","identifier":"gl","url":"https://www.tbs-sct.gc.ca/agreements-conventions/view-visualiser-eng.aspx?id=24#rates-gl","pay_scales":[{"name":"GL-AIM-9","steps":0,"current_pay":null,"increments":null},{"name":"GL-AIM-10","steps":0,"current_pay":null,"increments":null},{"name":"GL-AIM-11","steps":0,"current_pay":null,"increments":null},{"name":"GL-AIM-12","steps":0,"current_pay":null,"increments":null},{"name":"GL-AIM-13","steps":0,"current_pay":null,"increments":null},{"name":"GL-AIM-14","steps":0,"current_pay":null,"increments":null},{"name":"GL-AMW-1","steps":0,"current_pay":null,"increments":null},{"name":"GL-AMW-2","steps":0,"current_pay":null,"increments":null},{"name":"GL-AMW-3","steps":0,"current_pay":null,"increments":null},{"name":"GL-AMW-4","steps":0,"current_pay":null,"increments":null},{"name":"GL-AMW-5","steps":0,"current_pay":null,"increments":null},{"name":"GL-AMW-6","steps":0,"current_pay":null,"increments":null},{"name":"GL-AMW-7","steps":0,"current_pay":null,"increments":null},{"name":"GL-AMW-8","steps":0,"current_pay":null,"increments":null},{"name":"GL-AMW-9","steps":0,"current_pay":null,"increments":null},{"name":"GL-AMW-10","steps":0,"current_pay":null,"increments":null},{"name":"GL-AMW-11","steps":0,"current_pay":null,"increments":null},{"name":"GL-AMW-12","steps":0,"current_pay":null,"increments":null},{"name":"GL-AMW-13","steps":0,"current_pay":null,"increments":null},{"name":"GL-AMW-14","steps":0,"current_pay":null,"increments":null},{"name":"GL-COI-9","steps":0,"current_pay":null,"increments":null},{"name":"GL-COI-10","steps":0,"current_pay":null,"increments":null},{"name":"GL-COI-11","steps":0,"current_pay":null,"increments":null},{"name":"GL-COI-12","steps":0,"current_pay":null,"increments":null},{"name":"GL-COI-13","steps":0,"current_pay":null,"increments":null},{"name":"GL-COI-14","steps":0,"current_pay":null,"increments":null},{"name":"GL-EIM-9","steps":0,"current_pay":null,"increments":null},{"name":"GL-EIM-10","steps":0,"current_pay":null,"increments":null},{"name":"GL-EIM-11","steps":0,"current_pay":null,"increments":null},{"name":"GL-EIM-12","steps":0,"current_pay":null,"increments":null},{"name":"GL-EIM-13","steps":0,"current_pay":null,"increments":null},{"name":"GL-EIM-14","steps":0,"current_pay":null,"increments":null},{"name":"GL-ELE-1","steps":0,"current_pay":null,"increments":null},{"name":"GL-ELE-2","steps":0,"current_pay":null,"increments":null},{"name":"GL-ELE-3","steps":0,"current_pay":null,"increments":null},{"name":"GL-ELE-4","steps":0,"current_pay":null,"increments":null},{"name":"GL-ELE-5","steps":0,"current_pay":null,"increments":null},{"name":"GL-ELE-6","steps":0,"current_pay":null,"increments":null},{"name":"GL-ELE-7","steps":0,"current_pay":null,"increments":null},{"name":"GL-ELE-8","steps":0,"current_pay":null,"increments":null},{"name":"GL-ELE-9","steps":0,"current_pay":null,"increments":null},{"name":"GL-ELE-10","steps":0,"current_pay":null,"increments":null},{"name":"GL-ELE-11","steps":0,"current_pay":null,"increments":null},{"name":"GL-ELE-12","steps":0,"current_pay":null,"increments":null},{"name":"GL-ELE-13","steps":0,"current_pay":null,"increments":null},{"name":"GL-ELE-14","steps":0,"current_pay":null,"increments":null},{"name":"GL-GHW-3","steps":0,"current_pay":null,"increments":null},{"name":"GL-GHW-4","steps":0,"current_pay":null,"increments":null},{"name":"GL-GHW-5","steps":0,"current_pay":null,"increments":null},{"name":"GL-GHW-6","steps":0,"current_pay":null,"increments":null},{"name":"GL-GHW-7","steps":0,"current_pay":null,"increments":null},{"name":"GL-GHW-8","steps":0,"current_pay":null,"increments":null},{"name":"GL-GHW-9","steps":0,"current_pay":null,"increments":null},{"name":"GL-GHW-10","steps":0,"current_pay":null,"increments":null},{"name":"GL-GHW-11","steps":0,"current_pay":null,"increments":null},{"name":"GL-GHW-12","steps":0,"current_pay":null,"increments":null},{"name":"GL-INM-9","steps":0,"current_pay":null,"increments":null},{"name":"GL-INM-10","steps":0,"current_pay":null,"increments":null},{"name":"GL-INM-11","steps":0,"current_pay":null,"increments":null},{"name":"GL-INM-12","steps":0,"current_pay":null,"increments":null},{"name":"GL-INM-13","steps":0,"current_pay":null,"increments":null},{"name":"GL-INM-14","steps":0,"current_pay":null,"increments":null},{"name":"GL-MAM-5","steps":0,"current_pay":null,"increments":null},{"name":"GL-MAM-6","steps":0,"current_pay":null,"increments":null},{"name":"GL-MAM-7","steps":0,"current_pay":null,"increments":null},{"name":"GL-MAM-8","steps":0,"current_pay":null,"increments":null},{"name":"GL-MAM-9","steps":0,"current_pay":null,"increments":null},{"name":"GL-MAM-10","steps":0,"current_pay":null,"increments":null},{"name":"GL-MAM-11","steps":0,"current_pay":null,"increments":null},{"name":"GL-MAM-12","steps":0,"current_pay":null,"increments":null},{"name":"GL-MAM-13","steps":0,"current_pay":null,"increments":null},{"name":"GL-MAM-14","steps":0,"current_pay":null,"increments":null},{"name":"GL-MAN-1","steps":0,"current_pay":null,"increments":null},{"name":"GL-MAN-2","steps":0,"current_pay":null,"increments":null},{"name":"GL-MAN-3","steps":0,"current_pay":null,"increments":null},{"name":"GL-MAN-4","steps":0,"current_pay":null,"increments":null},{"name":"GL-MAN-5","steps":0,"current_pay":null,"increments":null},{"name":"GL-MAN-6","steps":0,"current_pay":null,"increments":null},{"name":"GL-MAN-7","steps":0,"current_pay":null,"increments":null},{"name":"GL-MAN-8","steps":0,"current_pay":null,"increments":null},{"name":"GL-MAN-9","steps":0,"current_pay":null,"increments":null},{"name":"GL-MAN-10","steps":0,"current_pay":null,"increments":null},{"name":"GL-MAN-11","steps":0,"current_pay":null,"increments":null},{"name":"GL-MAN-12","steps":0,"current_pay":null,"increments":null},{"name":"GL-MAN-13","steps":0,"current_pay":null,"increments":null},{"name":"GL-MAN-14","steps":0,"current_pay":null,"increments":null},{"name":"GL-MDO-1","steps":0,"current_pay":null,"increments":null},{"name":"GL-MDO-2","steps":0,"current_pay":null,"increments":null},{"name":"GL-MDO-3","steps":0,"current_pay":null,"increments":null},{"name":"GL-MDO-4","steps":0,"current_pay":null,"increments":null},{"name":"GL-MDO-5","steps":0,"current_pay":null,"increments":null},{"name":"GL-MDO-6","steps":0,"current_pay":null,"increments":null},{"name":"GL-MDO-7","steps":0,"current_pay":null,"increments":null},{"name":"GL-MDO-8","steps":0,"current_pay":null,"increments":null},{"name":"GL-MDO-9","steps":0,"current_pay":null,"increments":null},{"name":"GL-MDO-10","steps":0,"current_pay":null,"increments":null},{"name":"GL-MDO-11","steps":0,"current_pay":null,"increments":null},{"name":"GL-MDO-12","steps":0,"current_pay":null,"increments":null},{"name":"GL-MDO-13","steps":0,"current_pay":null,"increments":null},{"name":"GL-MDO-14","steps":0,"current_pay":null,"increments":null},{"name":"GL-MOC-1","steps":0,"current_pay":null,"increments":null},{"name":"GL-MOC-2","steps":0,"current_pay":null,"increments":null},{"name":"GL-MOC-3","steps":0,"current_pay":null,"increments":null},{"name":"GL-MOC-4","steps":0,"current_pay":null,"increments":null},{"name":"GL-MOC-5","steps":0,"current_pay":null,"increments":null},{"name":"GL-MOC-6","steps":0,"current_pay":null,"increments":null},{"name":"GL-MOC-7","steps":0,"current_pay":null,"increments":null},{"name":"GL-MOC-8","steps":0,"current_pay":null,"increments":null},{"name":"GL-MOC-9","steps":0,"current_pay":null,"increments":null},{"name":"GL-MOC-10","steps":0,"current_pay":null,"increments":null},{"name":"GL-MOC-11","steps":0,"current_pay":null,"increments":null},{"name":"GL-MOC-12","steps":0,"current_pay":null,"increments":null},{"name":"GL-MOC-13","steps":0,"current_pay":null,"increments":null},{"name":"GL-MOC-14","steps":0,"current_pay":null,"increments":null},{"name":"GL-MST-9","steps":0,"current_pay":null,"increments":null},{"name":"GL-MST-10","steps":0,"current_pay":null,"increments":null},{"name":"GL-MST-11","steps":0,"current_pay":null,"increments":null},{"name":"GL-MST-12","steps":0,"current_pay":null,"increments":null},{"name":"GL-MST-13","steps":0,"current_pay":null,"increments":null},{"name":"GL-MST-14","steps":0,"current_pay":null,"increments":null},{"name":"GL-PCF-6","steps":0,"current_pay":null,"increments":null},{"name":"GL-PCF-7","steps":0,"current_pay":null,"increments":null},{"name":"GL-PCF-8","steps":0,"current_pay":null,"increments":null},{"name":"GL-PCF-9","steps":0,"current_pay":null,"increments":null},{"name":"GL-PCF-10","steps":0,"current_pay":null,"increments":null},{"name":"GL-PCF-11","steps":0,"current_pay":null,"increments":null},{"name":"GL-PCF-12","steps":0,"current_pay":null,"increments":null},{"name":"GL-PCF-13","steps":0,"current_pay":null,"increments":null},{"name":"GL-PCF-14","steps":0,"current_pay":null,"increments":null},{"name":"GL-PIP-9","steps":0,"current_pay":null,"increments":null},{"name":"GL-PIP-10","steps":0,"current_pay":null,"increments":null},{"name":"GL-PIP-11","steps":0,"current_pay":null,"increments":null},{"name":"GL-PIP-12","steps":0,"current_pay":null,"increments":null},{"name":"GL-PIP-13","steps":0,"current_pay":null,"increments":null},{"name":"GL-PIP-14","steps":0,"current_pay":null,"increments":null},{"name":"GL-PRW-5","steps":0,"current_pay":null,"increments":null},{"name":"GL-PRW-6","steps":0,"current_pay":null,"increments":null},{"name":"GL-PRW-7","steps":0,"current_pay":null,"increments":null},{"name":"GL-PRW-8","steps":0,"current_pay":null,"increments":null},{"name":"GL-PRW-9","steps":0,"current_pay":null,"increments":null},{"name":"GL-PRW-10","steps":0,"current_pay":null,"increments":null},{"name":"GL-PRW-11","steps":0,"current_pay":null,"increments":null},{"name":"GL-PRW-12","steps":0,"current_pay":null,"increments":null},{"name":"GL-PRW-13","steps":0,"current_pay":null,"increments":null},{"name":"GL-PRW-14","steps":0,"current_pay":null,"increments":null},{"name":"GL-SMW-8","steps":0,"current_pay":null,"increments":null},{"name":"GL-SMW-9","steps":0,"current_pay":null,"increments":null},{"name":"GL-SMW-10","steps":0,"current_pay":null,"increments":null},{"name":"GL-SMW-11","steps":0,"current_pay":null,"increments":null},{"name":"GL-SMW-12","steps":0,"current_pay":null,"increments":null},{"name":"GL-SMW-13","steps":0,"current_pay":null,"increments":null},{"name":"GL-SMW-14","steps":0,"current_pay":null,"increments":null},{"name":"GL-VHE-8","steps":0,"current_pay":null,"increments":null},{"name":"GL-VHE-9","steps":0,"current_pay":null,"increments":null},{"name":"GL-VHE-10","steps":0,"current_pay":null,"increments":null},{"name":"GL-VHE-11","steps":0,"current_pay":null,"increments":null},{"name":"GL-VHE-12","steps":0,"current_pay":null,"increments":null},{"name":"GL-VHE-13","steps":0,"current_pay":null,"increments":null},{"name":"GL-VHE-14","steps":0,"current_pay":null,"increments":null},{"name":"GL-WOW-9","steps":0,"current_pay":null,"increments":null},{"name":"GL-WOW-10","steps":0,"current_pay":null,"increments":null},{"name":"GL-WOW-11","steps":0,"current_pay":null,"increments":null},{"name":"GL-WOW-12","steps":0,"current_pay":null,"increments":null},{"name":"GL-WOW-13","steps":0,"current_pay":null,"increments":null},{"name":"GL-WOW-14","steps":0,"current_pay":null,"increments":null}],"date_scraped":"2020-05-14 21:36:15.711153913 -0400 EDT m=+18.926601884","irregular_format":true}